cardiffwaste/__init__.py
cardiffwaste/cardiffwaste.py
cardiffwaste/const.py
cardiffwaste-0.2.6.dist-info/LICENCE.md
cardiffwaste-0.2.6.dist-info/METADATA
cardiffwaste-0.2.6.dist-info/WHEEL
cardiffwaste-0.2.6.dist-info/top_level.txt
cardiffwaste-0.2.6.dist-info/RECORD
