Metadata-Version: 2.1
Name: cardiffwaste
Version: 0.2.6
Summary: A package to gather waste collection details for UK addresses served by Cardiff Council.
Home-page: https://github.com/tombrien/cardiffwastepy
Author: Tom Brien
Author-email: tom@tombrien.io
Project-URL: Bug Tracker, https://github.com/tombrien/cardiffwastepy/issues
Classifier: Programming Language :: Python :: 3
Classifier: License :: OSI Approved :: MIT License
Classifier: Operating System :: OS Independent
Requires-Python: >=3.7
License-File: LICENCE.md
Requires-Dist: bs4
Requires-Dist: getuseragent
Requires-Dist: httpx
Requires-Dist: lxml
